tesseract_robotics-0.5.1.dist-info/RECORD
tesseract_robotics-0.5.1.dist-info/WHEEL
tesseract_robotics-0.5.1.dist-info/top_level.txt
tesseract_robotics-0.5.1.dist-info/METADATA
tesseract_robotics/__init__.py
tesseract_robotics/tesseract_collision/__init__.py
tesseract_robotics/tesseract_collision/tesseract_collision_python.py
tesseract_robotics/tesseract_collision/_tesseract_collision_python.so
tesseract_robotics/tesseract_srdf/__init__.py
tesseract_robotics/tesseract_srdf/tesseract_srdf_python.py
tesseract_robotics/tesseract_srdf/_tesseract_srdf_python.so
tesseract_robotics/tesseract_motion_planners_trajopt/__init__.py
tesseract_robotics/tesseract_motion_planners_trajopt/_tesseract_motion_planners_trajopt_python.so
tesseract_robotics/tesseract_motion_planners_trajopt/tesseract_motion_planners_trajopt_python.py
tesseract_robotics/tesseract_command_language/__init__.py
tesseract_robotics/tesseract_command_language/tesseract_command_language_python.py
tesseract_robotics/tesseract_command_language/_tesseract_command_language_python.so
tesseract_robotics/tesseract_state_solver/tesseract_state_solver_python.py
tesseract_robotics/tesseract_state_solver/__init__.py
tesseract_robotics/tesseract_state_solver/_tesseract_state_solver_python.so
tesseract_robotics/tesseract_scene_graph/tesseract_scene_graph_python.py
tesseract_robotics/tesseract_scene_graph/__init__.py
tesseract_robotics/tesseract_scene_graph/_tesseract_scene_graph_python.so
tesseract_robotics/tesseract_motion_planners/tesseract_motion_planners_python.py
tesseract_robotics/tesseract_motion_planners/__init__.py
tesseract_robotics/tesseract_motion_planners/_tesseract_motion_planners_python.so
tesseract_robotics/tesseract_motion_planners_descartes/tesseract_motion_planners_descartes_python.py
tesseract_robotics/tesseract_motion_planners_descartes/__init__.py
tesseract_robotics/tesseract_motion_planners_descartes/_tesseract_motion_planners_descartes_python.so
tesseract_robotics/.dylibs/libyaml-cpp.0.8.0.dylib
tesseract_robotics/.dylibs/libboost_regex.1.86.0.dylib
tesseract_robotics/.dylibs/libtesseract_motion_planners_simple.dylib
