Metadata-Version: 2.2
Name: tesseract-robotics
Version: 0.5.1
Summary: Tesseract Python Library
Home-page: https://tesseract-robotics.github.io/tesseract_python/
Author: John Wason
Author-email: wason@wasontech.com
License: Apache-2.0
Project-URL: Documentation, https://tesseract-robotics.github.io/tesseract_python/
Project-URL: Source, https://github.com/tesseract-robotics/tesseract_python
Project-URL: Tracker, https://github.com/tesseract-robotics/tesseract_python/issues
Requires-Dist: numpy
Dynamic: author
Dynamic: author-email
Dynamic: description
Dynamic: description-content-type
Dynamic: home-page
Dynamic: license
Dynamic: project-url
Dynamic: requires-dist
Dynamic: summary
